[
    {
        "id": "285",
        "codename": "Lancet-2"
    },
    {
        "id": "286",
        "codename": "Castle-3"
    },
    {
        "id": "376",
        "codename": "THRM-EX"
    },
    {
        "id": "4000",
        "codename": "正义骑士号"
    },
    {
        "id": "4077",
        "codename": "泰拉大陆调查团"
    },
    {
        "id": "4091",
        "codename": "U-Official"
    },
    {
        "id": "4093",
        "codename": "Friston-3"
    },
    {
        "id": "4136",
        "codename": "PhonoR-0"
    },
    {
        "id": "502",
        "codename": "夜刀"
    },
    {
        "id": "500",
        "codename": "黑角"
    },
    {
        "id": "503",
        "codename": "巡林者"
    },
    {
        "id": "501",
        "codename": "杜林"
    },
    {
        "id": "009",
        "codename": "12F"
    },
    {
        "id": "123",
        "codename": "芬"
    },
    {
        "id": "240",
        "codename": "香草"
    },
    {
        "id": "504",
        "codename": "预备干员-近战"
    },
    {
        "id": "192",
        "codename": "翎羽"
    },
    {
        "id": "208",
        "codename": "玫兰莎"
    },
    {
        "id": "281",
        "codename": "泡普卡"
    },
    {
        "id": "209",
        "codename": "卡缇"
    },
    {
        "id": "122",
        "codename": "米格鲁"
    },
    {
        "id": "514",
        "codename": "预备干员-重装"
    },
    {
        "id": "284",
        "codename": "斑点"
    },
    {
        "id": "124",
        "codename": "克洛丝"
    },
    {
        "id": "211",
        "codename": "安德切尔"
    },
    {
        "id": "507",
        "codename": "预备干员-狙击"
    },
    {
        "id": "121",
        "codename": "炎熔"
    },
    {
        "id": "120",
        "codename": "芙蓉"
    },
    {
        "id": "212",
        "codename": "安赛尔"
    },
    {
        "id": "506",
        "codename": "预备干员-后勤"
    },
    {
        "id": "210",
        "codename": "史都华德"
    },
    {
        "id": "505",
        "codename": "预备干员-术师"
    },
    {
        "id": "278",
        "codename": "梓兰"
    },
    {
        "id": "141",
        "codename": "夜烟"
    },
    {
        "id": "109",
        "codename": "远山"
    },
    {
        "id": "253",
        "codename": "格雷伊"
    },
    {
        "id": "328",
        "codename": "卡达"
    },
    {
        "id": "469",
        "codename": "深靛"
    },
    {
        "id": "4004",
        "codename": "布丁"
    },
    {
        "id": "235",
        "codename": "杰西卡"
    },
    {
        "id": "126",
        "codename": "流星"
    },
    {
        "id": "190",
        "codename": "红云"
    },
    {
        "id": "133",
        "codename": "梅"
    },
    {
        "id": "118",
        "codename": "白雪"
    },
    {
        "id": "440",
        "codename": "松果"
    },
    {
        "id": "302",
        "codename": "安比尔"
    },
    {
        "id": "366",
        "codename": "酸糖"
    },
    {
        "id": "4062",
        "codename": "铅踝"
    },
    {
        "id": "4100",
        "codename": "跃跃"
    },
    {
        "id": "198",
        "codename": "讯使"
    },
    {
        "id": "149",
        "codename": "清道夫"
    },
    {
        "id": "290",
        "codename": "红豆"
    },
    {
        "id": "151",
        "codename": "桃金娘"
    },
    {
        "id": "452",
        "codename": "豆苗"
    },
    {
        "id": "130",
        "codename": "杜宾"
    },
    {
        "id": "289",
        "codename": "缠丸"
    },
    {
        "id": "159",
        "codename": "断罪者"
    },
    {
        "id": "193",
        "codename": "霜叶"
    },
    {
        "id": "127",
        "codename": "艾丝黛尔"
    },
    {
        "id": "185",
        "codename": "慕斯"
    },
    {
        "id": "301",
        "codename": "刻刀"
    },
    {
        "id": "337",
        "codename": "宴"
    },
    {
        "id": "271",
        "codename": "芳汀"
    },
    {
        "id": "4067",
        "codename": "罗小黑"
    },
    {
        "id": "4063",
        "codename": "石英"
    },
    {
        "id": "491",
        "codename": "休谟斯"
    },
    {
        "id": "237",
        "codename": "砾"
    },
    {
        "id": "272",
        "codename": "孑"
    },
    {
        "id": "236",
        "codename": "暗索"
    },
    {
        "id": "117",
        "codename": "末药"
    },
    {
        "id": "187",
        "codename": "嘉维尔"
    },
    {
        "id": "298",
        "codename": "苏苏洛"
    },
    {
        "id": "181",
        "codename": "调香师"
    },
    {
        "id": "385",
        "codename": "清流"
    },
    {
        "id": "4041",
        "codename": "褐果"
    },
    {
        "id": "199",
        "codename": "角峰"
    },
    {
        "id": "150",
        "codename": "蛇屠箱"
    },
    {
        "id": "381",
        "codename": "泡泡"
    },
    {
        "id": "4130",
        "codename": "露托"
    },
    {
        "id": "196",
        "codename": "古米"
    },
    {
        "id": "260",
        "codename": "坚雷"
    },
    {
        "id": "110",
        "codename": "深海色"
    },
    {
        "id": "183",
        "codename": "地灵"
    },
    {
        "id": "258",
        "codename": "波登可"
    },
    {
        "id": "484",
        "codename": "罗比菈塔"
    },
    {
        "id": "355",
        "codename": "伊桑"
    },
    {
        "id": "277",
        "codename": "阿消"
    },
    {
        "id": "4107",
        "codename": "维荻"
    },
    {
        "id": "128",
        "codename": "白面鸮"
    },
    {
        "id": "275",
        "codename": "微风"
    },
    {
        "id": "115",
        "codename": "凛冬"
    },
    {
        "id": "102",
        "codename": "德克萨斯"
    },
    {
        "id": "349",
        "codename": "贾维"
    },
    {
        "id": "488",
        "codename": "青枳"
    },
    {
        "id": "513",
        "codename": "郁金香"
    },
    {
        "id": "4023",
        "codename": "红隼"
    },
    {
        "id": "261",
        "codename": "苇草"
    },
    {
        "id": "496",
        "codename": "野鬃"
    },
    {
        "id": "1036",
        "codename": "历阵锐枪芬"
    },
    {
        "id": "401",
        "codename": "极境"
    },
    {
        "id": "4119",
        "codename": "万顷"
    },
    {
        "id": "476",
        "codename": "夜半"
    },
    {
        "id": "497",
        "codename": "晓歌"
    },
    {
        "id": "4017",
        "codename": "谜图"
    },
    {
        "id": "308",
        "codename": "诗怀雅"
    },
    {
        "id": "265",
        "codename": "鞭刃"
    },
    {
        "id": "4106",
        "codename": "苍苔"
    },
    {
        "id": "4125",
        "codename": "医生"
    },
    {
        "id": "106",
        "codename": "芙兰卡"
    },
    {
        "id": "131",
        "codename": "炎客"
    },
    {
        "id": "154",
        "codename": "摩根"
    },
    {
        "id": "508",
        "codename": "Sharp"
    },
    {
        "id": "155",
        "codename": "因陀罗"
    },
    {
        "id": "415",
        "codename": "燧石"
    },
    {
        "id": "157",
        "codename": "达格达"
    },
    {
        "id": "140",
        "codename": "拉普兰德"
    },
    {
        "id": "294",
        "codename": "断崖"
    },
    {
        "id": "194",
        "codename": "烈夏"
    },
    {
        "id": "4083",
        "codename": "铎铃"
    },
    {
        "id": "252",
        "codename": "柏喙"
    },
    {
        "id": "459",
        "codename": "战车"
    },
    {
        "id": "143",
        "codename": "幽灵鲨"
    },
    {
        "id": "356",
        "codename": "布洛卡"
    },
    {
        "id": "4126",
        "codename": "导火索"
    },
    {
        "id": "274",
        "codename": "星极"
    },
    {
        "id": "333",
        "codename": "铸铁"
    },
    {
        "id": "475",
        "codename": "赤冬"
    },
    {
        "id": "1030",
        "codename": "火龙S黑角"
    },
    {
        "id": "421",
        "codename": "羽毛笔"
    },
    {
        "id": "4066",
        "codename": "海沫"
    },
    {
        "id": "486",
        "codename": "龙舌兰"
    },
    {
        "id": "4131",
        "codename": "奥达"
    },
    {
        "id": "129",
        "codename": "蓝毒"
    },
    {
        "id": "204",
        "codename": "白金"
    },
    {
        "id": "367",
        "codename": "灰喉"
    },
    {
        "id": "511",
        "codename": "Stormeye"
    },
    {
        "id": "365",
        "codename": "四月"
    },
    {
        "id": "1021",
        "codename": "寒芒克洛丝"
    },
    {
        "id": "498",
        "codename": "隐现"
    },
    {
        "id": "219",
        "codename": "陨星"
    },
    {
        "id": "379",
        "codename": "慑砂"
    },
    {
        "id": "4078",
        "codename": "截云"
    },
    {
        "id": "279",
        "codename": "送葬人"
    },
    {
        "id": "346",
        "codename": "奥斯塔"
    },
    {
        "id": "002",
        "codename": "阿米娅"
    },
    {
        "id": "405",
        "codename": "苦艾"
    },
    {
        "id": "411",
        "codename": "特米米"
    },
    {
        "id": "466",
        "codename": "雪绒"
    },
    {
        "id": "166",
        "codename": "天火"
    },
    {
        "id": "509",
        "codename": "Pith"
    },
    {
        "id": "306",
        "codename": "惊蛰"
    },
    {
        "id": "135",
        "codename": "星源"
    },
    {
        "id": "344",
        "codename": "蜜蜡"
    },
    {
        "id": "373",
        "codename": "莱恩哈特"
    },
    {
        "id": "341",
        "codename": "寒檀"
    },
    {
        "id": "388",
        "codename": "薄绿"
    },
    {
        "id": "338",
        "codename": "爱丽丝"
    },
    {
        "id": "297",
        "codename": "和弦"
    },
    {
        "id": "4110",
        "codename": "戴菲恩"
    },
    {
        "id": "1011",
        "codename": "炎狱炎熔"
    },
    {
        "id": "489",
        "codename": "蚀清"
    },
    {
        "id": "446",
        "codename": "阿罗玛"
    },
    {
        "id": "4013",
        "codename": "耶拉"
    },
    {
        "id": "4040",
        "codename": "洛洛"
    },
    {
        "id": "4054",
        "codename": "至简"
    },
    {
        "id": "499",
        "codename": "折光"
    },
    {
        "id": "4081",
        "codename": "温米"
    },
    {
        "id": "242",
        "codename": "梅尔"
    },
    {
        "id": "336",
        "codename": "稀音"
    },
    {
        "id": "108",
        "codename": "赫默"
    },
    {
        "id": "171",
        "codename": "华法琳"
    },
    {
        "id": "345",
        "codename": "亚叶"
    },
    {
        "id": "510",
        "codename": "Touch"
    },
    {
        "id": "348",
        "codename": "锡兰"
    },
    {
        "id": "436",
        "codename": "絮雨"
    },
    {
        "id": "402",
        "codename": "图耶"
    },
    {
        "id": "473",
        "codename": "桑葚"
    },
    {
        "id": "449",
        "codename": "蜜莓"
    },
    {
        "id": "4114",
        "codename": "哈洛德"
    },
    {
        "id": "1024",
        "codename": "濯尘芙蓉"
    },
    {
        "id": "494",
        "codename": "刺玫"
    },
    {
        "id": "4071",
        "codename": "明椒"
    },
    {
        "id": "148",
        "codename": "临光"
    },
    {
        "id": "226",
        "codename": "吽"
    },
    {
        "id": "4109",
        "codename": "深律"
    },
    {
        "id": "144",
        "codename": "红"
    },
    {
        "id": "243",
        "codename": "槐琥"
    },
    {
        "id": "214",
        "codename": "卡夫卡"
    },
    {
        "id": "455",
        "codename": "乌有"
    },
    {
        "id": "107",
        "codename": "雷蛇"
    },
    {
        "id": "201",
        "codename": "可颂"
    },
    {
        "id": "325",
        "codename": "拜松"
    },
    {
        "id": "163",
        "codename": "火神"
    },
    {
        "id": "378",
        "codename": "石棉"
    },
    {
        "id": "512",
        "codename": "暮落"
    },
    {
        "id": "4047",
        "codename": "车尔尼"
    },
    {
        "id": "457",
        "codename": "闪击"
    },
    {
        "id": "304",
        "codename": "暴雨"
    },
    {
        "id": "431",
        "codename": "灰毫"
    },
    {
        "id": "493",
        "codename": "火哨"
    },
    {
        "id": "422",
        "codename": "极光"
    },
    {
        "id": "464",
        "codename": "洋灰"
    },
    {
        "id": "145",
        "codename": "普罗旺斯"
    },
    {
        "id": "4006",
        "codename": "玫拉"
    },
    {
        "id": "158",
        "codename": "守林人"
    },
    {
        "id": "218",
        "codename": "安哲拉"
    },
    {
        "id": "4014",
        "codename": "子月"
    },
    {
        "id": "363",
        "codename": "熔泉"
    },
    {
        "id": "4043",
        "codename": "埃拉托"
    },
    {
        "id": "1027",
        "codename": "承曦格雷伊"
    },
    {
        "id": "4104",
        "codename": "冰酿"
    },
    {
        "id": "4015",
        "codename": "空构"
    },
    {
        "id": "173",
        "codename": "崖心"
    },
    {
        "id": "383",
        "codename": "雪雉"
    },
    {
        "id": "4105",
        "codename": "杏仁"
    },
    {
        "id": "174",
        "codename": "初雪"
    },
    {
        "id": "254",
        "codename": "巫恋"
    },
    {
        "id": "195",
        "codename": "真理"
    },
    {
        "id": "326",
        "codename": "格劳克斯"
    },
    {
        "id": "4032",
        "codename": "但书"
    },
    {
        "id": "4122",
        "codename": "小满"
    },
    {
        "id": "433",
        "codename": "掠风"
    },
    {
        "id": "101",
        "codename": "空"
    },
    {
        "id": "4045",
        "codename": "海蒂"
    },
    {
        "id": "343",
        "codename": "月禾"
    },
    {
        "id": "4019",
        "codename": "九色鹿"
    },
    {
        "id": "492",
        "codename": "夏栎"
    },
    {
        "id": "4102",
        "codename": "凛视"
    },
    {
        "id": "215",
        "codename": "狮蝎"
    },
    {
        "id": "478",
        "codename": "绮良"
    },
    {
        "id": "241",
        "codename": "食铁兽"
    },
    {
        "id": "4036",
        "codename": "见行者"
    },
    {
        "id": "451",
        "codename": "罗宾"
    },
    {
        "id": "458",
        "codename": "霜华"
    },
    {
        "id": "369",
        "codename": "贝娜"
    },
    {
        "id": "4016",
        "codename": "风丸"
    },
    {
        "id": "4124",
        "codename": "双月"
    },
    {
        "id": "103",
        "codename": "能天使"
    },
    {
        "id": "332",
        "codename": "空弦"
    },
    {
        "id": "456",
        "codename": "灰烬"
    },
    {
        "id": "340",
        "codename": "黑"
    },
    {
        "id": "4055",
        "codename": "鸿雪"
    },
    {
        "id": "430",
        "codename": "远牙"
    },
    {
        "id": "113",
        "codename": "W"
    },
    {
        "id": "300",
        "codename": "菲亚梅塔"
    },
    {
        "id": "197",
        "codename": "早露"
    },
    {
        "id": "2012",
        "codename": "提丰"
    },
    {
        "id": "391",
        "codename": "迷迭香"
    },
    {
        "id": "1035",
        "codename": "维什戴尔"
    },
    {
        "id": "1013",
        "codename": "假日威龙陈"
    },
    {
        "id": "4117",
        "codename": "莱伊"
    },
    {
        "id": "112",
        "codename": "推进之王"
    },
    {
        "id": "222",
        "codename": "风笛"
    },
    {
        "id": "362",
        "codename": "嵯峨"
    },
    {
        "id": "479",
        "codename": "琴柳"
    },
    {
        "id": "420",
        "codename": "焰尾"
    },
    {
        "id": "427",
        "codename": "伺夜"
    },
    {
        "id": "249",
        "codename": "缪尔赛思"
    },
    {
        "id": "4087",
        "codename": "伊内丝"
    },
    {
        "id": "134",
        "codename": "伊芙利特"
    },
    {
        "id": "213",
        "codename": "莫斯提马"
    },
    {
        "id": "180",
        "codename": "艾雅法拉"
    },
    {
        "id": "2013",
        "codename": "刻俄柏"
    },
    {
        "id": "4027",
        "codename": "霍尔海雅"
    },
    {
        "id": "4133",
        "codename": "逻各斯"
    },
    {
        "id": "2015",
        "codename": "夕"
    },
    {
        "id": "472",
        "codename": "异客"
    },
    {
        "id": "426",
        "codename": "卡涅利安"
    },
    {
        "id": "4080",
        "codename": "林"
    },
    {
        "id": "377",
        "codename": "澄闪"
    },
    {
        "id": "4046",
        "codename": "黑键"
    },
    {
        "id": "206",
        "codename": "灵知"
    },
    {
        "id": "291",
        "codename": "安洁莉娜"
    },
    {
        "id": "358",
        "codename": "铃兰"
    },
    {
        "id": "248",
        "codename": "麦哲伦"
    },
    {
        "id": "1012",
        "codename": "浊心斯卡蒂"
    },
    {
        "id": "4134",
        "codename": "魔王"
    },
    {
        "id": "1031",
        "codename": "淬羽赫默"
    },
    {
        "id": "2023",
        "codename": "令"
    },
    {
        "id": "4072",
        "codename": "白铁"
    },
    {
        "id": "245",
        "codename": "塑心"
    },
    {
        "id": "250",
        "codename": "傀影"
    },
    {
        "id": "1028",
        "codename": "缄默德克萨斯"
    },
    {
        "id": "1029",
        "codename": "麒麟R夜刀"
    },
    {
        "id": "322",
        "codename": "老鲤"
    },
    {
        "id": "1033",
        "codename": "琳琅诗怀雅"
    },
    {
        "id": "400",
        "codename": "温蒂"
    },
    {
        "id": "225",
        "codename": "阿"
    },
    {
        "id": "474",
        "codename": "歌蕾蒂娅"
    },
    {
        "id": "437",
        "codename": "水月"
    },
    {
        "id": "4132",
        "codename": "阿斯卡纶"
    },
    {
        "id": "1023",
        "codename": "归溟幽灵鲨"
    },
    {
        "id": "4048",
        "codename": "多萝西"
    },
    {
        "id": "4123",
        "codename": "艾拉"
    },
    {
        "id": "147",
        "codename": "闪灵"
    },
    {
        "id": "179",
        "codename": "夜莺"
    },
    {
        "id": "003",
        "codename": "凯尔希"
    },
    {
        "id": "4042",
        "codename": "流明"
    },
    {
        "id": "1016",
        "codename": "纯烬艾雅法拉"
    },
    {
        "id": "1020",
        "codename": "焰影苇草"
    },
    {
        "id": "136",
        "codename": "星熊"
    },
    {
        "id": "202",
        "codename": "塞雷娅"
    },
    {
        "id": "423",
        "codename": "瑕光"
    },
    {
        "id": "2025",
        "codename": "黍"
    },
    {
        "id": "2014",
        "codename": "年"
    },
    {
        "id": "311",
        "codename": "泥岩"
    },
    {
        "id": "4065",
        "codename": "斥罪"
    },
    {
        "id": "416",
        "codename": "森蚺"
    },
    {
        "id": "4039",
        "codename": "号角"
    },
    {
        "id": "1034",
        "codename": "涤火杰西卡"
    },
    {
        "id": "264",
        "codename": "山"
    },
    {
        "id": "2024",
        "codename": "重岳"
    },
    {
        "id": "172",
        "codename": "银灰"
    },
    {
        "id": "293",
        "codename": "棘刺"
    },
    {
        "id": "4082",
        "codename": "仇白"
    },
    {
        "id": "4088",
        "codename": "赫德雷"
    },
    {
        "id": "010",
        "codename": "陈"
    },
    {
        "id": "4009",
        "codename": "艾丽妮"
    },
    {
        "id": "4116",
        "codename": "锏"
    },
    {
        "id": "017",
        "codename": "煌"
    },
    {
        "id": "1026",
        "codename": "百炼嘉维尔"
    },
    {
        "id": "350",
        "codename": "史尔特尔"
    },
    {
        "id": "4098",
        "codename": "薇薇安娜"
    },
    {
        "id": "188",
        "codename": "赫拉格"
    },
    {
        "id": "4121",
        "codename": "左乐"
    },
    {
        "id": "485",
        "codename": "帕拉斯"
    },
    {
        "id": "1014",
        "codename": "耀骑士临光"
    },
    {
        "id": "4011",
        "codename": "止颂"
    },
    {
        "id": "1032",
        "codename": "圣约送葬人"
    },
    {
        "id": "4064",
        "codename": "玛恩纳"
    },
    {
        "id": "230",
        "codename": "暴行"
    },
    {
        "id": "282",
        "codename": "空爆"
    },
    {
        "id": "283",
        "codename": "月见夜"
    },
    {
        "id": "137",
        "codename": "猎蜂"
    },
    {
        "id": "347",
        "codename": "杰克"
    },
    {
        "id": "164",
        "codename": "夜魔"
    },
    {
        "id": "220",
        "codename": "格拉尼"
    },
    {
        "id": "263",
        "codename": "斯卡蒂"
    }
]